pipeup
