Metadata-Version: 1.1
Name: pipeup
Version: 0.1.8
Summary: A command line tool for piping to a webpage
Home-page: http://github.com/nathancahill/pipeup
Author: Nathan Cahill
Author-email: nathan@nathancahill.com
License: MIT
Download-URL: https://github.com/nathancahill/pipeup/tarball/0.1.8
Keywords: pipeup,pipe,stream,websockets
Platform: UNKNOWN
Classifier: Development Status :: 4 - Beta
Classifier: Intended Audience :: Developers
Classifier: License :: OSI Approved :: MIT License
Classifier: Programming Language :: Python :: 2.7
